{
  "type": "minecraft:block",
  "pools": [
    {
      "bonus_rolls": 0.0,
      "entries": [
        {
          "type": "minecraft:item",
          "conditions": [
            {
              "block": "ultramarine:blue_and_black_tile_slab",
              "condition": "minecraft:block_state_property",
              "properties": {
                "type": "top"
              }
            }
          ],
          "name": "ultramarine:blue_and_black_tile_slab"
        },
        {
          "type": "minecraft:item",
          "conditions": [
            {
              "block": "ultramarine:blue_and_black_tile_slab",
              "condition": "minecraft:block_state_property",
              "properties": {
                "type": "bottom"
              }
            }
          ],
          "name": "ultramarine:blue_and_black_tile_slab"
        },
        {
          "type": "minecraft:item",
          "conditions": [
            {
              "block": "ultramarine:blue_and_black_tile_slab",
              "condition": "minecraft:block_state_property",
              "properties": {
                "type": "double"
              }
            }
          ],
          "functions": [
            {
              "add": false,
              "count": 2.0,
              "function": "minecraft:set_count"
            }
          ],
          "name": "ultramarine:blue_and_black_tile_slab"
        }
      ],
      "name": "blue_and_black_tile_slab",
      "rolls": 1.0
    }
  ],
  "random_sequence": "ultramarine:blocks/blue_and_black_tile_slab"
}