{
  "type": "minecraft:crafting_shapeless",
  "ingredients": [
    {
      "item": "ultramarine:unfired_clay_brick"
    },
    {
      "item": "ultramarine:unfired_clay_brick"
    },
    {
      "item": "ultramarine:unfired_clay_brick"
    },
    {
      "item": "ultramarine:unfired_clay_brick"
    },
    {
      "item": "ultramarine:unfired_clay_brick"
    },
    {
      "item": "ultramarine:unfired_clay_brick"
    },
    {
      "item": "ultramarine:hematite_dust"
    }
  ],
  "result": {
    "item": "ultramarine:unfired_black_brick",
    "count": 6
  }
}